bibt/gcp/bq/__init__.py
bibt/gcp/bq/classes.py
bibt/gcp/bq/version.py
bibt_gcp_bq-0.0.27.dist-info/METADATA
bibt_gcp_bq-0.0.27.dist-info/WHEEL
bibt_gcp_bq-0.0.27.dist-info/licenses/LICENSE
bibt_gcp_bq-0.0.27.dist-info/RECORD
